streamlit_audio_recorder/__init__.py
streamlit_audio_recorder/st_app_main.py
streamlit_audio_recorder/st_audiorec/.DS_Store
streamlit_audio_recorder/st_audiorec/__init__.py
streamlit_audio_recorder/st_audiorec/frontend/.DS_Store
streamlit_audio_recorder/st_audiorec/frontend/.env
streamlit_audio_recorder/st_audiorec/frontend/.prettierrc
streamlit_audio_recorder/st_audiorec/frontend/build/.DS_Store
streamlit_audio_recorder/st_audiorec/frontend/build/asset-manifest.json
streamlit_audio_recorder/st_audiorec/frontend/build/bootstrap.min.css
streamlit_audio_recorder/st_audiorec/frontend/build/index.html
streamlit_audio_recorder/st_audiorec/frontend/build/precache-manifest.4829c060d313d0b0d13d9af3b0180289.js
streamlit_audio_recorder/st_audiorec/frontend/build/service-worker.js
streamlit_audio_recorder/st_audiorec/frontend/build/static/.DS_Store
streamlit_audio_recorder/st_audiorec/frontend/build/static/css/2.bfbf028b.chunk.css
streamlit_audio_recorder/st_audiorec/frontend/build/static/css/2.bfbf028b.chunk.css.map
streamlit_audio_recorder/st_audiorec/frontend/build/static/js/2.270b84d8.chunk.js
streamlit_audio_recorder/st_audiorec/frontend/build/static/js/2.270b84d8.chunk.js.LICENSE.txt
streamlit_audio_recorder/st_audiorec/frontend/build/static/js/2.270b84d8.chunk.js.map
streamlit_audio_recorder/st_audiorec/frontend/build/static/js/main.833ba252.chunk.js
streamlit_audio_recorder/st_audiorec/frontend/build/static/js/main.833ba252.chunk.js.map
streamlit_audio_recorder/st_audiorec/frontend/build/static/js/runtime-main.11ec9aca.js
streamlit_audio_recorder/st_audiorec/frontend/build/static/js/runtime-main.11ec9aca.js.map
streamlit_audio_recorder/st_audiorec/frontend/build/styles.css
streamlit_audio_recorder/st_audiorec/frontend/package-lock.json
streamlit_audio_recorder/st_audiorec/frontend/package.json
streamlit_audio_recorder/st_audiorec/frontend/public/.DS_Store
streamlit_audio_recorder/st_audiorec/frontend/public/bootstrap.min.css
st_audio_recorder-0.0.2.dist-info/WHEEL
st_audio_recorder-0.0.2.dist-info/METADATA
st_audio_recorder-0.0.2.dist-info/RECORD
