Metadata-Version: 2.1
Name: st-audio-recorder
Version: 0.0.2
Summary: 
Author: Stefan Rummer
Requires-Python: >=3.10,<4.0
Classifier: Programming Language :: Python :: 3
Classifier: Programming Language :: Python :: 3.10
Classifier: Programming Language :: Python :: 3.11
Requires-Dist: numpy (>=1.25.2,<2.0.0)
Requires-Dist: streamlit (>=1.26.0,<2.0.0)
